{
  "generated_at": "2026-07-22T05:10:17.131177+00:00",
  "wti": {
    "price": 85.41,
    "prev_close": 84.91,
    "change": 0.5,
    "pct": 0.59,
    "market_time": "2026-07-22T01:00:04-04:00",
    "spark": [
      85.27,
      85.26,
      85.35,
      85.4,
      85.37,
      85.26,
      85.36,
      85.37,
      85.39,
      85.38,
      85.41,
      85.43,
      85.43,
      85.41
    ],
    "source": "yahoo"
  },
  "hh": {
    "price": 2.872,
    "prev_close": 2.865,
    "change": 0.007,
    "pct": 0.24,
    "market_time": "2026-07-22T00:59:32-04:00",
    "spark": [
      2.879,
      2.879,
      2.877,
      2.878,
      2.876,
      2.874,
      2.873,
      2.875,
      2.872,
      2.872,
      2.872,
      2.872,
      2.872
    ],
    "source": "yahoo"
  }
}