{
  "generated_at": "2026-07-07T04:45:16.069530+00:00",
  "wti": {
    "price": 69.0,
    "prev_close": 68.55,
    "change": 0.45,
    "pct": 0.66,
    "market_time": "2026-07-07T00:35:08-04:00",
    "spark": [
      68.95,
      68.98,
      68.97,
      68.96,
      68.99,
      69.0,
      69.02,
      68.97,
      69.0
    ],
    "source": "yahoo"
  },
  "hh": {
    "price": 3.226,
    "prev_close": 3.245,
    "change": -0.019,
    "pct": -0.59,
    "market_time": "2026-07-07T00:35:15-04:00",
    "spark": [
      3.231,
      3.229,
      3.23,
      3.229,
      3.23,
      3.227,
      3.225,
      3.226
    ],
    "source": "yahoo"
  }
}